badar_calc/__init__.py
badar_calc/calculator.py
badar_calc-0.0.5.dist-info/LICENSE.txt
badar_calc-0.0.5.dist-info/METADATA
badar_calc-0.0.5.dist-info/WHEEL
badar_calc-0.0.5.dist-info/top_level.txt
badar_calc-0.0.5.dist-info/RECORD
