Metadata-Version: 2.1
Name: badar-calc
Version: 0.0.5
Summary: Very basic calculator
Home-page: UNKNOWN
Author: Badrudin Mohamed Ali
Author-email: badrudin.dev@gmail.com
License: MIT
Platform: UNKNOWN
Classifier: Development Status :: 5 - Production/Stable
Classifier: Intended Audience :: Education
Classifier: License :: OSI Approved :: MIT License
Classifier: Operating System :: Microsoft :: Windows :: Windows 10
Classifier: Programming Language :: Python :: 2
Classifier: Programming Language :: Python :: 3.5
